async_cassandra/__init__.py
async_cassandra/base.py
async_cassandra/cluster.py
async_cassandra/constants.py
async_cassandra/exceptions.py
async_cassandra/metrics.py
async_cassandra/monitoring.py
async_cassandra/py.typed
async_cassandra/result.py
async_cassandra/retry_policy.py
async_cassandra/session.py
async_cassandra/streaming.py
async_cassandra/utils.py
async_cassandra-0.0.1.dist-info/licenses/LICENSE
async_cassandra-0.0.1.dist-info/METADATA
async_cassandra-0.0.1.dist-info/WHEEL
async_cassandra-0.0.1.dist-info/top_level.txt
async_cassandra-0.0.1.dist-info/RECORD
