Metadata-Version: 2.4
Name: async-cassandra
Version: 0.0.1
Summary: Async Python wrapper for the Cassandra Python driver
Author: AxonOps
Maintainer: AxonOps
License: Apache-2.0
Project-URL: Homepage, https://github.com/axonops/async-python-cassandra-client
Project-URL: Bug Tracker, https://github.com/axonops/async-python-cassandra-client/issues
Project-URL: Documentation, https://async-python-cassandra-client.readthedocs.io
Project-URL: Source Code, https://github.com/axonops/async-python-cassandra-client
Project-URL: Company, https://axonops.com
Keywords: cassandra,async,asyncio,database,nosql
Classifier: Development Status :: 3 - Alpha
Classifier: Intended Audience :: Developers
Classifier: License :: OSI Approved :: Apache Software License
Classifier: Operating System :: OS Independent
Classifier: Programming Language :: Python
Classifier: Programming Language :: Python :: 3
Classifier: Programming Language :: Python :: 3.12
Classifier: Programming Language :: Python :: 3.13
Classifier: Programming Language :: Python :: 3 :: Only
Classifier: Programming Language :: Python :: Implementation :: CPython
Classifier: Topic :: Database
Classifier: Topic :: Database :: Database Engines/Servers
Classifier: Topic :: Software Development :: Libraries :: Python Modules
Classifier: Framework :: AsyncIO
Classifier: Typing :: Typed
Requires-Python: >=3.12
License-File: LICENSE
Requires-Dist: cassandra-driver>=3.29.2
Provides-Extra: dev
Requires-Dist: pytest>=7.0.0; extra == "dev"
Requires-Dist: pytest-asyncio>=0.21.0; extra == "dev"
Requires-Dist: pytest-cov>=4.0.0; extra == "dev"
Requires-Dist: pytest-mock>=3.10.0; extra == "dev"
Requires-Dist: pytest-timeout>=2.2.0; extra == "dev"
Requires-Dist: black>=23.0.0; extra == "dev"
Requires-Dist: isort>=5.12.0; extra == "dev"
Requires-Dist: ruff>=0.1.0; extra == "dev"
Requires-Dist: mypy>=1.0.0; extra == "dev"
Requires-Dist: pre-commit>=3.0.0; extra == "dev"
Provides-Extra: test
Requires-Dist: pytest>=7.0.0; extra == "test"
Requires-Dist: pytest-asyncio>=0.21.0; extra == "test"
Requires-Dist: pytest-cov>=4.0.0; extra == "test"
Requires-Dist: pytest-mock>=3.10.0; extra == "test"
Requires-Dist: pytest-timeout>=2.2.0; extra == "test"
Requires-Dist: pytest-bdd>=7.0.0; extra == "test"
Requires-Dist: fastapi>=0.100.0; extra == "test"
Requires-Dist: httpx>=0.24.0; extra == "test"
Requires-Dist: uvicorn>=0.23.0; extra == "test"
Requires-Dist: psutil>=5.9.0; extra == "test"
Provides-Extra: docs
Requires-Dist: sphinx>=6.0.0; extra == "docs"
Requires-Dist: sphinx-rtd-theme>=1.2.0; extra == "docs"
Requires-Dist: sphinx-autodoc-typehints>=1.22.0; extra == "docs"
Dynamic: license-file
